folderforge/__init__.py
folderforge/__main__.py
folderforge/core.py
folderforge/models/__init__.py
folderforge/models/file.py
folderforge/services/__init__.py
folderforge/services/change_directory_context.py
folderforge/services/file_service.py
folderforge/services/folderforge_service.py
folderforge/utils/__init__.py
folderforge/utils/constants.py
folderforge/utils/enums.py
folderforge/utils/functions.py
folderforge/utils/styles.py
tests/__init__.py
tests/ignore_this_test.py
folderforge-1.0.1.dist-info/LICENSE
folderforge-1.0.1.dist-info/METADATA
folderforge-1.0.1.dist-info/WHEEL
folderforge-1.0.1.dist-info/entry_points.txt
folderforge-1.0.1.dist-info/top_level.txt
folderforge-1.0.1.dist-info/RECORD
