Metadata-Version: 2.1
Name: folderforge
Version: 1.0.1
Summary: FolderForge is a Python utility for creating directory structures based on a description file in JSON format.
Home-page: https://github.com/StenTech/FolderForge
Author: StenTech
Author-email: phd.sten.tech@gmail.com
Project-URL: Bug Tracker, https://github.com/StenTech/FolderForge/log-module/issues
Classifier: Programming Language :: Python :: 3
Classifier: License :: OSI Approved :: MIT License
Classifier: Operating System :: OS Independent
Requires-Python: >=3.9
License-File: LICENSE
Requires-Dist: requests ==2.28.2
